{
  "data": {
    "sector": "Industrials",
    "slug": "industrials",
    "tickers": [
      {
        "ticker": "TRMD",
        "name": "Torm plc",
        "owner_count": 1,
        "conviction_score": 21,
        "direction": "BUY"
      },
      {
        "ticker": "CP",
        "name": "Canadian Pacific Kansas City",
        "owner_count": 2,
        "conviction_score": 0,
        "direction": "NEUTRAL"
      },
      {
        "ticker": "CNDT",
        "name": "Conduent",
        "owner_count": 1,
        "conviction_score": 0,
        "direction": "NEUTRAL"
      }
    ],
    "top_managers": [
      {
        "slug": "howard-marks",
        "name": "Howard Marks",
        "fund": "Oaktree Capital",
        "sector_pct": 14.8
      },
      {
        "slug": "david-einhorn",
        "name": "David Einhorn",
        "fund": "Greenlight Capital",
        "sector_pct": 9.8
      },
      {
        "slug": "chris-hohn",
        "name": "Chris Hohn",
        "fund": "TCI Fund Management",
        "sector_pct": 8.6
      },
      {
        "slug": "bill-ackman",
        "name": "Bill Ackman",
        "fund": "Pershing Square Capital",
        "sector_pct": 6.8
      }
    ],
    "flow": {
      "2025-Q4": {
        "net": 3,
        "buys": 1,
        "sells": 0
      },
      "2025-Q3": {
        "net": 3,
        "buys": 1,
        "sells": 0
      },
      "2025-Q2": {
        "net": 3,
        "buys": 1,
        "sells": 0
      },
      "2025-Q1": {
        "net": 0,
        "buys": 0,
        "sells": 0
      },
      "2024-Q4": {
        "net": 3,
        "buys": 1,
        "sells": 0
      },
      "2024-Q3": {
        "net": 3,
        "buys": 1,
        "sells": 0
      },
      "2024-Q2": {
        "net": 3,
        "buys": 1,
        "sells": 0
      },
      "2024-Q1": {
        "net": 3,
        "buys": 1,
        "sells": 0
      }
    },
    "stats": {
      "ticker_count": 3,
      "total_owners": 4,
      "avg_conviction": 7,
      "net_flow_4q": 9,
      "strong_buys": 1,
      "strong_sells": 0
    },
    "permalink": "https://holdlens.com/sector/industrials"
  },
  "meta": {
    "generated_at": "2026-04-15T16:56:40.423Z",
    "quarter": "2025-Q4",
    "quarter_label": "Q4 2025",
    "source": "HoldLens",
    "license": "Free for personal and commercial use. Attribution appreciated.",
    "docs": "https://holdlens.com/docs",
    "quarters": [
      "2025-Q4",
      "2025-Q3",
      "2025-Q2",
      "2025-Q1",
      "2024-Q4",
      "2024-Q3",
      "2024-Q2",
      "2024-Q1"
    ]
  }
}